dataforge/__init__.py
dataforge/databricks_sql.py
dataforge/importProject.py
dataforge/main.py
dataforge/mainConfig.py
dataforge/miniSparky.py
dataforge/pg.py
dataforge/util.py
dataforge/resources/log4j2.properties
dataforge/resources/pg_deploy.sql
dataforge/resources/project/meta.yaml
dataforge/resources/project/relations.yaml
dataforge/resources/project/outputs/feature_customer.yaml
dataforge/resources/project/sources/tpch_customer.yaml
dataforge/resources/project/sources/tpch_lineitem.yaml
dataforge/resources/project/sources/tpch_nations.yaml
dataforge/resources/project/sources/tpch_orders.yaml
dataforge/resources/project/sources/tpch_part.yaml
dataforge/resources/project/sources/tpch_partsupp.yaml
dataforge/resources/project/sources/tpch_region.yaml
dataforge/resources/project/sources/tpch_supplier.yaml
dataforge_core-1.3.4.dist-info/licenses/LICENSE
dataforge_core-1.3.4.dist-info/METADATA
dataforge_core-1.3.4.dist-info/WHEEL
dataforge_core-1.3.4.dist-info/entry_points.txt
dataforge_core-1.3.4.dist-info/top_level.txt
dataforge_core-1.3.4.dist-info/RECORD
