Metadata-Version: 2.4
Name: dataforge-core
Version: 1.3.4
Summary: Command line compiler for dataforge core projects
Author-email: Vadim Orlov <vorlov@dataforgelabs.com>
Project-URL: Homepage, https://github.com/dataforgelabs/dataforge-core
Project-URL: Issues, https://github.com/dataforgelabs/dataforge-core/issues
Requires-Python: >=3.12
License-File: LICENSE
Requires-Dist: pyyaml
Requires-Dist: psycopg2-binary
Requires-Dist: pyspark
Requires-Dist: importlib_resources
Requires-Dist: databricks-sql-connector
Requires-Dist: sql-formatter
Requires-Dist: psutil
Dynamic: license-file
